pyfeyn2/__init__.py
pyfeyn2/feynmandiagram.py
pyfeyn2/mkfeyndiag.py
pyfeyn2/version.py
pyfeyn2/version.pyi
pyfeyn2/auto/__init__.py
pyfeyn2/auto/bend.py
pyfeyn2/auto/debug.py
pyfeyn2/auto/diagram.py
pyfeyn2/auto/label.py
pyfeyn2/auto/position.py
pyfeyn2/interface/dot.py
pyfeyn2/interface/hepmc.py
pyfeyn2/interface/qgraf.py
pyfeyn2/render/__init__.py
pyfeyn2/render/all.py
pyfeyn2/render/render.py
pyfeyn2/render/js/__init__.py
pyfeyn2/render/js/mermaid.py
pyfeyn2/render/latex/__init__.py
pyfeyn2/render/latex/dot.py
pyfeyn2/render/latex/feynmp.py
pyfeyn2/render/latex/latex.py
pyfeyn2/render/latex/metapost.py
pyfeyn2/render/latex/tikzfeynman.py
pyfeyn2/render/mpl/feynmanrender.py
pyfeyn2/render/ps/madgraph.py
pyfeyn2/render/pyx/__init__.py
pyfeyn2/render/pyx/blobs.py
pyfeyn2/render/pyx/config.py
pyfeyn2/render/pyx/deco.py
pyfeyn2/render/pyx/diagrams.py
pyfeyn2/render/pyx/lines.py
pyfeyn2/render/pyx/paint.py
pyfeyn2/render/pyx/points.py
pyfeyn2/render/pyx/pyxrender.py
pyfeyn2/render/pyx/utils.py
pyfeyn2/render/root/pyfeyn.py
pyfeyn2/render/root/rootpdfrender.py
pyfeyn2/render/root/rootrender.py
pyfeyn2/render/text/ascii.py
pyfeyn2/render/text/asciipdf.py
pyfeyn2/render/text/plainpdf.py
pyfeyn2/render/text/unicode.py
pyfeyn2/render/text/unicodepdf.py
pyfeyn2-2.4.3.dist-info/METADATA
pyfeyn2-2.4.3.dist-info/WHEEL
pyfeyn2-2.4.3.dist-info/licenses/AUTHORS
pyfeyn2-2.4.3.dist-info/licenses/LICENSE
pyfeyn2-2.4.3.dist-info/RECORD
