Metadata-Version: 2.4
Name: pyfeyn2
Version: 2.4.3
Summary: PyFeyn is a package which makes drawing Feynman diagrams simple and programmatic.  Feynman diagrams are important constructs in perturbative field theory, so being able to draw them in a programmatic fashion is important if attempting to enumerate a large number of diagram configurations is important. The output quality of PyFeyn diagrams (into PDF or EPS formats) is very high, and special effects can be obtained by using constructs from PyX, which PyFeyn is based around
Project-URL: Documentation, https://github.com/APN-Pucky/pyfeyn2#readme
Project-URL: Issues, https://github.com/APN-Pucky/pyfeyn2/issues
Project-URL: Source, https://github.com/APN-Pucky/pyfeyn2/
Author-email: Alexander Puck Neuwirth <alexander@neuwirth-informatik.de>
License-File: AUTHORS
License-File: LICENSE
Keywords: HEP,diagram,feynman
Classifier: Development Status :: 4 - Beta
Classifier: Intended Audience :: Developers
Classifier: Intended Audience :: Science/Research
Classifier: License :: OSI Approved :: BSD License
Classifier: Programming Language :: Python
Classifier: Programming Language :: Python :: 3.8
Classifier: Programming Language :: Python :: 3.9
Classifier: Programming Language :: Python :: 3.10
Classifier: Programming Language :: Python :: 3.11
Classifier: Programming Language :: Python :: 3.12
Classifier: Programming Language :: Python :: 3.13
Classifier: Programming Language :: Python :: Implementation :: CPython
Classifier: Programming Language :: Python :: Implementation :: PyPy
Classifier: Topic :: Scientific/Engineering
Requires-Python: >=3.8
Requires-Dist: apn-dot2tex>=2.11.10
Requires-Dist: asciidraw>=0.1.2
Requires-Dist: feynman>=2.1
Requires-Dist: feynml
Requires-Dist: feynml[interfaces]>=0.3.1
Requires-Dist: graphviz
Requires-Dist: iminuit
Requires-Dist: ipyparallel
Requires-Dist: matplotlib
Requires-Dist: numpy
Requires-Dist: pydot
Requires-Dist: pygments
Requires-Dist: pylatex
Requires-Dist: pylatexenc
Requires-Dist: pyx
Requires-Dist: wand
Provides-Extra: dev
Requires-Dist: ipython; extra == 'dev'
Requires-Dist: jupyter; extra == 'dev'
Requires-Dist: jupyterlab; extra == 'dev'
Requires-Dist: pre-commit; extra == 'dev'
Provides-Extra: docs
Requires-Dist: jupyter-sphinx; extra == 'docs'
Requires-Dist: myst-parser; extra == 'docs'
Requires-Dist: nbsphinx; extra == 'docs'
Requires-Dist: sphinx-autobuild; extra == 'docs'
Requires-Dist: sphinx-math-dollar; extra == 'docs'
Requires-Dist: sphinx-rtd-theme; extra == 'docs'
Requires-Dist: sphinx<8.0.0; extra == 'docs'
Requires-Dist: sphinxcontrib-napoleon; extra == 'docs'
Requires-Dist: tomli; extra == 'docs'
Provides-Extra: lint
Requires-Dist: ruff; extra == 'lint'
Provides-Extra: test
Requires-Dist: pytest; extra == 'test'
Requires-Dist: pytest-cov; extra == 'test'
